lsd/__init__.py
lsd/post/__init__.py
lsd/post/agglomerate.py
lsd/post/fragments.py
lsd/post/graph_merge.py
lsd/post/local_segmentation.py
lsd/post/merge_tree.cpython-311-darwin.so
lsd/post/parallel_aff_agglomerate.py
lsd/post/parallel_fragments.py
lsd/post/parallel_lsd_agglomerate.py
lsd/post/rag.py
lsd/post/shared_rag_provider.py
lsd/post/persistence/__init__.py
lsd/post/persistence/mongodb_rag_provider.py
lsd/post/persistence/sqlite_rag_provider.py
lsd/train/__init__.py
lsd/train/local_shape_descriptor.py
lsd/train/gp/__init__.py
lsd/train/gp/add_local_shape_descriptor.py
lsds-0.1.3.dist-info/LICENSE
lsds-0.1.3.dist-info/METADATA
lsds-0.1.3.dist-info/WHEEL
lsds-0.1.3.dist-info/top_level.txt
lsds-0.1.3.dist-info/RECORD
