Metadata-Version: 2.1
Name: lsds
Version: 0.1.3
Summary: Local Shape Descriptors.
Home-page: https://github.com/funkey/lsd
Author: Jan Funke
Author-email: funkej@janelia.hhmi.org
License: MIT
License-File: LICENSE
Requires-Dist: numpy
Requires-Dist: scipy
Requires-Dist: h5py
Requires-Dist: scikit-image
Requires-Dist: requests
Requires-Dist: cython
Requires-Dist: gunpowder
